django_logging/__init__.py
django_logging/apps.py
django_logging/cursor_wrapper.py
django_logging/handlers.py
django_logging/log_object.py
django_logging/logger.py
django_logging/middleware.py
django_logging/settings.py
django_logging_json-1.15.dist-info/DESCRIPTION.rst
django_logging_json-1.15.dist-info/METADATA
django_logging_json-1.15.dist-info/RECORD
django_logging_json-1.15.dist-info/WHEEL
django_logging_json-1.15.dist-info/metadata.json
django_logging_json-1.15.dist-info/top_level.txt
