Metadata-Version: 2.0
Name: django-logging-json
Version: 1.15
Summary: A simple Django app to log requests/responses in various formats, such as JSON.
Home-page: https://github.com/cipriantarta/django-logging
Author: Ciprian Tarta
Author-email: me@cipriantarta.ro
License: BSD
Keywords: django logging json
Platform: UNKNOWN
Classifier: Environment :: Web Environment
Classifier: Framework :: Django
Classifier: Intended Audience :: Developers
Classifier: License :: OSI Approved :: BSD License
Classifier: Operating System :: OS Independent
Classifier: Programming Language :: Python :: 2.6
Classifier: Programming Language :: Python :: 2.7
Classifier: Programming Language :: Python :: 3.5
Classifier: Programming Language :: Python :: 3.6
Classifier: Topic :: Software Development :: Libraries :: Python Modules
Classifier: Framework :: Django
Classifier: Framework :: Django :: 1.4
Classifier: Framework :: Django :: 1.5
Classifier: Framework :: Django :: 1.6
Classifier: Framework :: Django :: 1.7
Classifier: Framework :: Django :: 1.8
Classifier: Framework :: Django :: 1.9
Classifier: Framework :: Django :: 1.10
Requires-Dist: django (>=1.4)
Requires-Dist: six
Requires-Dist: elasticsearch (>=2.0.0)
Requires-Dist: certifi
